{
    "mainEntry": {
      "facing" : "north",
      "position" : [4, 1, 0]
    },
    "replacements" : {
      "oak" : { "type" : "woodType", "state" : 2 }
    },
    "air" : {
      "preferredAirMode" : 2,
      "replacements" : [
        [0, 1, 5, 0, 3, 6],
        [1, 1, 4, 1, 3, 8],
        [2, 1, 2, 2, 3, 11],
        [3, 1, 1, 3, 3, 12],
        [4, 1, 0, 4, 3, 12],
        [5, 1, 1, 5, 3, 13],
        [6, 1, 1, 6, 3, 12],
        [7, 1, 2, 7, 3, 12],
        [8, 1, 3, 8, 3, 11],
        [9, 1, 4, 9, 3, 9],
        [10, 1, 5, 10, 3, 7]
      ]
    },
    "lootTables" : [
    ],
    "villageInfo" : {
      "villager" : 0
    },
    "ground" : {
      "zones" : [
        [0, 5, 0, 6],
        [1, 4, 1, 8],
        [2, 2, 2, 11],
        [3, 1, 3, 12],
        [4, 0, 4, 12],
        [5, 1, 5, 13],
        [6, 1, 6, 12],
        [7, 2, 7, 12],
        [8, 3, 8, 11],
        [9, 4, 9, 9],
        [10, 5, 10, 7]
      ]
    },
    "special" : {
      "sign" : [
          { "position" : [5, 1, 2], "orientation" : "north"},
          { "position" : [6, 1, 9], "orientation" : "east"},
          { "position" : [9, 1, 5], "orientation" : "east"},
          { "position" : [3, 1, 8], "orientation" : "south"},
          { "position" : [7, 1, 10], "orientation" : "south"}
      ]
    }, 
    "sign" : {
      "position" : [9, 2, 0],
      "facing" : "north",
      "tier" : 1,
      "name" : "Graveyard"
    }
  }